axdscfg/__init__.py
axdscfg/axdscfg.py
axdscfg/credentials.py
axdscfg/exceptions.py
axdscfg/utils.py
axdscfg-1.0.1.dist-info/LICENSE
axdscfg-1.0.1.dist-info/METADATA
axdscfg-1.0.1.dist-info/WHEEL
axdscfg-1.0.1.dist-info/entry_points.txt
axdscfg-1.0.1.dist-info/top_level.txt
axdscfg-1.0.1.dist-info/RECORD
