Metadata-Version: 2.1
Name: axdscfg
Version: 1.0.1
Summary: Python lib to get credentials from encrypted file.
Home-page: https://pypi.org/project/axdscfg
Author: Axiomas Data Science
Author-email: suporte@axiomas.tech
License: GNU General Public License v3 (GPLv3)
Platform: UNKNOWN
Classifier: Programming Language :: Python :: 3
Classifier: License :: OSI Approved :: GNU General Public License v3 (GPLv3)
Classifier: Operating System :: Unix
Requires-Python: >=3.5
Requires-Dist: configparser (>=3.7.4)
Requires-Dist: PyNaCl (==1.3.0)
